pgmer/Exce_postion.py
pgmer/__init__.py
pgmer-2.0.2.dist-info/LICENSE
pgmer-2.0.2.dist-info/METADATA
pgmer-2.0.2.dist-info/WHEEL
pgmer-2.0.2.dist-info/top_level.txt
pgmer-2.0.2.dist-info/RECORD
