Metadata-Version: 2.1
Name: pgmer
Version: 2.0.2
Summary: Tools for front-end engineering
Author: 小鱼程序员
Author-email: 732355054@qq.com
Keywords: python,front-end engineering,pyzjr,windows,mac,linux
Classifier: Development Status :: 4 - Beta
Classifier: Intended Audience :: Developers
Classifier: Programming Language :: Python :: 3
Classifier: Operating System :: Unix
Classifier: Operating System :: MacOS :: MacOS X
Classifier: Operating System :: Microsoft :: Windows
Requires-Python: >=3.8
License-File: LICENSE
Requires-Dist: websockets
Requires-Dist: requests
Requires-Dist: loguru
Requires-Dist: websocket-client
